beautifulday/__init__.py
beautifulday/make_soup.py
beautifulday/weather.py
beautifulday/weather_extended.py
beautifulday/weather_hourly.py
beautifulday-0.3.0.data/scripts/beautifulday
beautifulday-0.3.0.dist-info/DESCRIPTION.rst
beautifulday-0.3.0.dist-info/METADATA
beautifulday-0.3.0.dist-info/RECORD
beautifulday-0.3.0.dist-info/WHEEL
beautifulday-0.3.0.dist-info/metadata.json
beautifulday-0.3.0.dist-info/top_level.txt
