Metadata-Version: 2.0
Name: beautifulday
Version: 0.3.0
Summary: Learning about Webscraping
Home-page: https://www.linuxnorth.org/beautifulday/
Author: Al Audet
Author-email: alaudet@linuxnorth.org
License: MIT License
Download-URL: https://github.com/alaudet/beautifulday/releases
Platform: UNKNOWN
Classifier: Development Status :: 4 - Beta
Classifier: Environment :: Console
Classifier: Intended Audience :: End Users/Desktop
Classifier: Natural Language :: English
Classifier: Operating System :: POSIX :: Linux
Classifier: Programming Language :: Python :: 3
Classifier: Topic :: Utilities
Classifier: License :: OSI Approved :: MIT License
Requires-Dist: beautifulsoup4
Requires-Dist: requests
